tripletex/__init__.py
tripletex/__main__.py
tripletex/core/api.py
tripletex/core/client.py
tripletex/core/config.py
tripletex/core/crud.py
tripletex/core/models.py
tripletex/endpoints/activity/crud.py
tripletex/endpoints/activity/models.py
tripletex/endpoints/bank/__init__.py
tripletex/endpoints/bank/crud/__init__.py
tripletex/endpoints/bank/crud/bank.py
tripletex/endpoints/bank/crud/internal_match.py
tripletex/endpoints/bank/crud/reconciliation.py
tripletex/endpoints/bank/crud/reconciliation_entry.py
tripletex/endpoints/bank/crud/statement.py
tripletex/endpoints/bank/crud/statement_transaction.py
tripletex/endpoints/bank/crud/transaction_comment.py
tripletex/endpoints/bank/models/__init__.py
tripletex/endpoints/bank/models/internal_match.py
tripletex/endpoints/company/crud.py
tripletex/endpoints/company/models.py
tripletex/endpoints/country/crud.py
tripletex/endpoints/country/models.py
tripletex/endpoints/department/crud.py
tripletex/endpoints/department/models.py
tripletex/endpoints/employee/crud.py
tripletex/endpoints/employee/models.py
tripletex/endpoints/ledger/crud/__init__.py
tripletex/endpoints/ledger/crud/account.py
tripletex/endpoints/ledger/crud/accounting_period.py
tripletex/endpoints/ledger/crud/annual_account.py
tripletex/endpoints/ledger/crud/close_group.py
tripletex/endpoints/ledger/crud/ledger.py
tripletex/endpoints/ledger/crud/payment_type_out.py
tripletex/endpoints/ledger/crud/posting.py
tripletex/endpoints/ledger/crud/posting_rules.py
tripletex/endpoints/ledger/crud/vat_type.py
tripletex/endpoints/ledger/crud/voucher.py
tripletex/endpoints/ledger/crud/voucher_historical.py
tripletex/endpoints/ledger/crud/voucher_opening_balance.py
tripletex/endpoints/ledger/crud/voucher_type.py
tripletex/endpoints/ledger/models/__init__.py
tripletex/endpoints/ledger/models/account.py
tripletex/endpoints/ledger/models/accounting_period.py
tripletex/endpoints/ledger/models/annual_account.py
tripletex/endpoints/ledger/models/close_group.py
tripletex-0.1.8.dist-info/LICENSE
tripletex-0.1.8.dist-info/METADATA
tripletex-0.1.8.dist-info/WHEEL
tripletex-0.1.8.dist-info/RECORD
