Metadata-Version: 2.3
Name: tripletex
Version: 0.1.8
Summary: An efficient and user-friendly Python library crafted specifically for seamless integration with Tripletex's accounting and financial management APIs.
License: Proprietary
Keywords: crud,api,client,rest,tripletex,accounting,financial,management
Author: Leikaab
Author-email: nordavindltd@gmail.com
Requires-Python: >=3.10,<4.0
Classifier: License :: OSI Approved :: GNU Lesser General Public License v3 or later (LGPLv3+)
Classifier: License :: Other/Proprietary License
Classifier: Programming Language :: Python :: 3
Classifier: Programming Language :: Python :: 3.10
Classifier: Programming Language :: Python :: 3.11
Classifier: Programming Language :: Python :: 3.12
Classifier: Programming Language :: Python :: 3.13
Requires-Dist: crudclient (==0.7.0)
Project-URL: Bug Tracker, https://github.com/Leikaab/tripletex/issues
Project-URL: Documentation, https://github.com/Leikaab/tripletex#readme
Project-URL: Homepage, https://github.com/Leikaab/tripletex
Project-URL: Repository, https://github.com/Leikaab/tripletex
